README.md
setup.py
upload_haddocks.egg-info/PKG-INFO
upload_haddocks.egg-info/SOURCES.txt
upload_haddocks.egg-info/dependency_links.txt
upload_haddocks.egg-info/entry_points.txt
upload_haddocks.egg-info/not-zip-safe
upload_haddocks.egg-info/requires.txt
upload_haddocks.egg-info/top_level.txt
uploadhaddocks/__init__.py
uploadhaddocks/__main__.py
uploadhaddocks/util.py