Metadata-Version: 1.1
Name: upload-haddocks
Version: 0.4
Summary: Fix up Haskell documentation and upload it to Hackage
Home-page: https://github.com/rcook/upload-haddocks
Author: Richard Cook
Author-email: rcook@rcook.org
License: MIT
Platform: UNKNOWN
Classifier: Development Status :: 3 - Alpha
Classifier: License :: OSI Approved :: MIT License
Classifier: Programming Language :: Python :: 2.7
